pyarmor_runtime_000000/__init__.py
pyarmor_runtime_000000/pyarmor_runtime.pyd
visaionserver/__init__.py
visaionserver/run.py
visaionserver/script.py
visaionserver/api/__init__.py
visaionserver/api/deps.py
visaionserver/api/v1/__init__.py
visaionserver/api/v1/annotations.py
visaionserver/api/v1/api_models.py
visaionserver/api/v1/auth.py
visaionserver/api/v1/datasets.py
visaionserver/api/v1/evaluation.py
visaionserver/api/v1/export.py
visaionserver/api/v1/health.py
visaionserver/api/v1/inference.py
visaionserver/api/v1/job_scheduler.py
visaionserver/api/v1/labels.py
visaionserver/api/v1/logs.py
visaionserver/api/v1/models.py
visaionserver/api/v1/projects.py
visaionserver/api/v1/samples.py
visaionserver/api/v1/tags.py
visaionserver/core/__init__.py
visaionserver/core/constant.py
visaionserver/core/logger.py
visaionserver/core/settings.py
visaionserver/core/version.py
visaionserver/db/base.py
visaionserver/db/database.py
visaionserver/db/session.py
visaionserver/models/__init__.py
visaionserver/models/ai_model.py
visaionserver/models/cache.py
visaionserver/models/dataset.py
visaionserver/models/dataset_sample.py
visaionserver/models/db_model.py
visaionserver/models/export.py
visaionserver/models/label.py
visaionserver/models/logs.py
visaionserver/models/project.py
visaionserver/models/project_pin.py
visaionserver/models/sample.py
visaionserver/models/sample_label.py
visaionserver/models/tag.py
visaionserver/models/user.py
visaionserver/schemas/annotation.py
visaionserver/schemas/common.py
visaionserver/schemas/dataset.py
visaionserver/schemas/export.py
visaionserver/schemas/label.py
visaionserver/schemas/logs.py
visaionserver/schemas/project.py
visaionserver/schemas/sample.py
visaionserver/schemas/tag.py
visaionserver/schemas/user.py
visaionserver/services/annotation.py
visaionserver/services/auth.py
visaionserver/services/common.py
visaionserver/services/dataset.py
visaionserver/services/dataset_split_optimized.py
visaionserver/services/export.py
visaionserver-0.5.3.dist-info/METADATA
visaionserver-0.5.3.dist-info/WHEEL
visaionserver-0.5.3.dist-info/entry_points.txt
visaionserver-0.5.3.dist-info/top_level.txt
visaionserver-0.5.3.dist-info/RECORD
