Metadata-Version: 2.4
Name: visaionserver
Version: 0.5.3
Summary: visaion is a deeplearningplatform for detection, segmentation, classification.
Author-email: Felix Fu <alanmathisonturing@163.com>, Wei Wei <alanmathisonturing@163.com>
Maintainer-email: Felix Fu <alanmathisonturing@163.com>
License: AGPL-3.0
Keywords: machine-learning,deep-learning,computer-vision,ML,DL,AI
Classifier: Development Status :: 4 - Beta
Classifier: Intended Audience :: Developers
Classifier: Intended Audience :: Education
Classifier: Intended Audience :: Science/Research
Classifier: License :: OSI Approved :: GNU Affero General Public License v3 or later (AGPLv3+)
Classifier: Programming Language :: Python :: 3
Classifier: Programming Language :: Python :: 3.10
Classifier: Programming Language :: Python :: 3.11
Classifier: Programming Language :: Python :: 3.12
Classifier: Topic :: Software Development
Classifier: Topic :: Scientific/Engineering
Classifier: Topic :: Scientific/Engineering :: Artificial Intelligence
Classifier: Topic :: Scientific/Engineering :: Image Recognition
Classifier: Operating System :: POSIX :: Linux
Classifier: Operating System :: MacOS
Classifier: Operating System :: Microsoft :: Windows
Requires-Python: >=3.10
Requires-Dist: py-cpuinfo>=9.0.0
Requires-Dist: psutil>=6.1.1
Requires-Dist: fastapi==0.115.7
Requires-Dist: uvicorn==0.34.0
Requires-Dist: pynvml==12.0.0
Requires-Dist: cos-python-sdk-v5==1.9.33
Requires-Dist: sqlalchemy==2.0.31
Requires-Dist: aiosqlite==0.20.0
Requires-Dist: python-jose==3.3.0
Requires-Dist: APScheduler==3.11.0
Requires-Dist: email-validator==2.2.0
Requires-Dist: passlib==1.7.4
Requires-Dist: greenlet==3.1.1
Requires-Dist: bcrypt==4.2.1
Requires-Dist: Pillow==11.1.0
Requires-Dist: python-multipart==0.0.20
Requires-Dist: pytz==2025.1
Requires-Dist: pywin32==308; sys_platform == "win32"
Requires-Dist: sqlmodel==0.0.24
Requires-Dist: alembic==1.15.1
